{
  "task": "fsm_tracking",
  "model": "E88",
  "dim": 128,
  "depth": 4,
  "seq_len": 256,
  "batch_size": 32,
  "lr": 0.0003,
  "seed": 42,
  "params": 330912,
  "random_baseline_acc": 0.25,
  "steps": [
    {
      "step": 0,
      "train_loss": 1.4199604988098145,
      "eval_acc": 0.248321533203125,
      "eval_loss": 1.398305743932724,
      "elapsed_s": 12.585168838500977
    },
    {
      "step": 150,
      "train_loss": 0.7101943492889404,
      "eval_acc": 0.506622314453125,
      "eval_loss": 0.7106077969074249,
      "elapsed_s": 72.31304788589478
    },
    {
      "step": 300,
      "train_loss": 0.6871789693832397,
      "eval_acc": 0.506744384765625,
      "eval_loss": 0.6876216381788254,
      "elapsed_s": 129.79820346832275
    },
    {
      "step": 450,
      "train_loss": 0.29459208250045776,
      "eval_acc": 0.926177978515625,
      "eval_loss": 0.22994088754057884,
      "elapsed_s": 187.21480798721313
    },
    {
      "step": 600,
      "train_loss": 0.00878620520234108,
      "eval_acc": 1.0,
      "eval_loss": 0.00904244533739984,
      "elapsed_s": 241.7580418586731
    },
    {
      "step": 750,
      "train_loss": 0.0023272475227713585,
      "eval_acc": 1.0,
      "eval_loss": 0.0023263165494427085,
      "elapsed_s": 294.1603558063507
    },
    {
      "step": 900,
      "train_loss": 0.001355829183012247,
      "eval_acc": 1.0,
      "eval_loss": 0.0013860369799658656,
      "elapsed_s": 350.85480213165283
    },
    {
      "step": 1050,
      "train_loss": 0.0009977985173463821,
      "eval_acc": 1.0,
      "eval_loss": 0.0009954115812433884,
      "elapsed_s": 405.23070216178894
    },
    {
      "step": 1200,
      "train_loss": 0.0007212673081085086,
      "eval_acc": 1.0,
      "eval_loss": 0.00071347487391904,
      "elapsed_s": 460.0984809398651
    },
    {
      "step": 1350,
      "train_loss": 0.000563944922760129,
      "eval_acc": 1.0,
      "eval_loss": 0.0005672917468473315,
      "elapsed_s": 511.3763053417206
    },
    {
      "step": 1500,
      "train_loss": 0.0004492590087465942,
      "eval_acc": 1.0,
      "eval_loss": 0.0004479444760363549,
      "elapsed_s": 562.6806554794312
    },
    {
      "step": 1650,
      "train_loss": 0.0003617645415943116,
      "eval_acc": 1.0,
      "eval_loss": 0.0003721760949702002,
      "elapsed_s": 615.280416727066
    },
    {
      "step": 1800,
      "train_loss": 0.0003034207329619676,
      "eval_acc": 1.0,
      "eval_loss": 0.00032268445647787303,
      "elapsed_s": 668.408994436264
    },
    {
      "step": 1950,
      "train_loss": 0.0002571034710854292,
      "eval_acc": 1.0,
      "eval_loss": 0.0002726564562181011,
      "elapsed_s": 722.8133721351624
    },
    {
      "step": 2100,
      "train_loss": 0.00022087254910729825,
      "eval_acc": 1.0,
      "eval_loss": 0.0002279852888023015,
      "elapsed_s": 775.2276351451874
    },
    {
      "step": 2250,
      "train_loss": 0.00019175896886736155,
      "eval_acc": 1.0,
      "eval_loss": 0.00019753206652239896,
      "elapsed_s": 828.9936747550964
    },
    {
      "step": 2400,
      "train_loss": 0.0001633286738069728,
      "eval_acc": 1.0,
      "eval_loss": 0.00017281528562307358,
      "elapsed_s": 882.3188910484314
    },
    {
      "step": 2550,
      "train_loss": 0.00014459577505476773,
      "eval_acc": 1.0,
      "eval_loss": 0.00015447961777681485,
      "elapsed_s": 933.4410965442657
    },
    {
      "step": 2700,
      "train_loss": 0.00012790836626663804,
      "eval_acc": 1.0,
      "eval_loss": 0.00013581731036538258,
      "elapsed_s": 981.3742010593414
    },
    {
      "step": 2850,
      "train_loss": 0.0001125820999732241,
      "eval_acc": 1.0,
      "eval_loss": 0.00011814890058303718,
      "elapsed_s": 1031.2898511886597
    },
    {
      "step": 2999,
      "train_loss": 0.00010031120473286137,
      "eval_acc": 1.0,
      "eval_loss": 0.00010733726230682805,
      "elapsed_s": 1078.6518216133118
    }
  ],
  "final_acc": 1.0,
  "final_loss": 0.00010580682601357694,
  "elapsed_total_s": 1083.3819761276245
}