{
  "task": "parity",
  "model": "E88",
  "dim": 128,
  "depth": 4,
  "seq_len": 1024,
  "batch_size": 32,
  "lr": 0.0003,
  "seed": 123,
  "params": 167072,
  "random_baseline_acc": 0.5,
  "steps": [
    {
      "step": 0,
      "train_loss": 1.3585929870605469,
      "eval_acc": 0.493927001953125,
      "eval_loss": 1.2864584922790527,
      "elapsed_s": 17.65804648399353
    },
    {
      "step": 150,
      "train_loss": 0.6957646012306213,
      "eval_acc": 0.5018539428710938,
      "eval_loss": 0.6953746974468231,
      "elapsed_s": 208.05396056175232
    },
    {
      "step": 300,
      "train_loss": 0.00744792353361845,
      "eval_acc": 1.0,
      "eval_loss": 0.007383602089248598,
      "elapsed_s": 396.78031182289124
    },
    {
      "step": 450,
      "train_loss": 0.0023319516330957413,
      "eval_acc": 1.0,
      "eval_loss": 0.002341949671972543,
      "elapsed_s": 591.2229788303375
    },
    {
      "step": 600,
      "train_loss": 0.0012632198631763458,
      "eval_acc": 1.0,
      "eval_loss": 0.0012652494187932462,
      "elapsed_s": 788.3564307689667
    },
    {
      "step": 750,
      "train_loss": 0.0008129952475428581,
      "eval_acc": 1.0,
      "eval_loss": 0.0008174301037797704,
      "elapsed_s": 980.3378274440765
    },
    {
      "step": 900,
      "train_loss": 0.0005737353349104524,
      "eval_acc": 1.0,
      "eval_loss": 0.0005765203532064334,
      "elapsed_s": 1168.7265362739563
    },
    {
      "step": 1050,
      "train_loss": 0.00042887625750154257,
      "eval_acc": 1.0,
      "eval_loss": 0.0004310099466238171,
      "elapsed_s": 1359.6010146141052
    },
    {
      "step": 1200,
      "train_loss": 0.00033397990046069026,
      "eval_acc": 1.0,
      "eval_loss": 0.00033550511579960585,
      "elapsed_s": 1558.289370059967
    },
    {
      "step": 1350,
      "train_loss": 0.00026610965142026544,
      "eval_acc": 1.0,
      "eval_loss": 0.0002669549430720508,
      "elapsed_s": 1753.0113756656647
    },
    {
      "step": 1500,
      "train_loss": 0.00021585258946288377,
      "eval_acc": 1.0,
      "eval_loss": 0.00021692683003493585,
      "elapsed_s": 1943.7099251747131
    },
    {
      "step": 1650,
      "train_loss": 0.00017978536197915673,
      "eval_acc": 1.0,
      "eval_loss": 0.0001804992170946207,
      "elapsed_s": 2131.7176806926727
    },
    {
      "step": 1800,
      "train_loss": 0.00015048471686895937,
      "eval_acc": 1.0,
      "eval_loss": 0.00015108189109014347,
      "elapsed_s": 2321.769644498825
    },
    {
      "step": 1950,
      "train_loss": 0.00012861128197982907,
      "eval_acc": 1.0,
      "eval_loss": 0.00012904243703815155,
      "elapsed_s": 2517.979660987854
    },
    {
      "step": 2100,
      "train_loss": 0.00011060833639930934,
      "eval_acc": 1.0,
      "eval_loss": 0.00011067661580455024,
      "elapsed_s": 2707.6899979114532
    },
    {
      "step": 2250,
      "train_loss": 9.555069846101105e-05,
      "eval_acc": 1.0,
      "eval_loss": 9.618260446586646e-05,
      "elapsed_s": 2899.634665966034
    },
    {
      "step": 2400,
      "train_loss": 8.298960165120661e-05,
      "eval_acc": 1.0,
      "eval_loss": 8.341090324393008e-05,
      "elapsed_s": 3088.215816259384
    },
    {
      "step": 2550,
      "train_loss": 7.295908289961517e-05,
      "eval_acc": 1.0,
      "eval_loss": 7.327020648517646e-05,
      "elapsed_s": 3280.843168258667
    },
    {
      "step": 2700,
      "train_loss": 6.443435268010944e-05,
      "eval_acc": 1.0,
      "eval_loss": 6.473629218817223e-05,
      "elapsed_s": 3474.5668177604675
    },
    {
      "step": 2850,
      "train_loss": 5.6840024626581e-05,
      "eval_acc": 1.0,
      "eval_loss": 5.7009001466212794e-05,
      "elapsed_s": 3667.7316246032715
    },
    {
      "step": 2999,
      "train_loss": 5.061670526629314e-05,
      "eval_acc": 1.0,
      "eval_loss": 5.079952552478062e-05,
      "elapsed_s": 3856.4540479183197
    }
  ],
  "final_acc": 1.0,
  "final_loss": 5.0811698883990175e-05,
  "elapsed_total_s": 3874.1818318367004
}